qradar4py/__init__.py
qradar4py/api.py
qradar4py/endpoints/__init__.py
qradar4py/endpoints/access.py
qradar4py/endpoints/analytics.py
qradar4py/endpoints/api_endpoint.py
qradar4py/endpoints/application.py
qradar4py/endpoints/ariel.py
qradar4py/endpoints/asset_model.py
qradar4py/endpoints/auth.py
qradar4py/endpoints/backup_and_restore.py
qradar4py/endpoints/bandwidth_manager.py
qradar4py/endpoints/config.py
qradar4py/endpoints/configservices.py
qradar4py/endpoints/configuration.py
qradar4py/endpoints/dashboards.py
qradar4py/endpoints/data_classification.py
qradar4py/endpoints/disaster_recovery.py
qradar4py/endpoints/dynamic_search.py
qradar4py/endpoints/forensics.py
qradar4py/endpoints/g11n.py
qradar4py/endpoints/gui_app_framework.py
qradar4py/endpoints/health.py
qradar4py/endpoints/health_data.py
qradar4py/endpoints/help.py
qradar4py/endpoints/historical_correlation.py
qradar4py/endpoints/internal.py
qradar4py/endpoints/qni.py
qradar4py/endpoints/qrm.py
qradar4py/endpoints/qvm.py
qradar4py/endpoints/reference_data.py
qradar4py/endpoints/reporting.py
qradar4py/endpoints/reports.py
qradar4py/endpoints/scanner.py
qradar4py/endpoints/services.py
qradar4py/endpoints/siem.py
qradar4py/endpoints/staged_config.py
qradar4py/endpoints/support.py
qradar4py/endpoints/system.py
qradar4py/endpoints/usermanagement.py
qradar4py-3.0.dist-info/LICENSE
qradar4py-3.0.dist-info/METADATA
qradar4py-3.0.dist-info/WHEEL
qradar4py-3.0.dist-info/top_level.txt
qradar4py-3.0.dist-info/RECORD
