Metadata-Version: 2.1
Name: qradar4py
Version: 3.0
Summary: QRadarAPI Client written in Python
Home-page: https://github.com/ryukisec/qradar4py
Author: Ryuki
Author-email: ryuki@tuta.io
License: mit
Platform: UNKNOWN
Classifier: Development Status :: 4 - Beta
Classifier: License :: OSI Approved :: MIT License
Classifier: Natural Language :: English
Classifier: Operating System :: OS Independent
Classifier: Programming Language :: Python
Classifier: Topic :: Security
Requires-Python: >=3
Requires-Dist: requests
